BenchML-0.3.4.data/scripts/bbatch
BenchML-0.3.4.data/scripts/binfo
BenchML-0.3.4.data/scripts/binput
BenchML-0.3.4.data/scripts/bmark
BenchML-0.3.4.data/scripts/bmeta
BenchML-0.3.4.data/scripts/bml
benchml/__init__.py
benchml/accumulator.py
benchml/analysis.py
benchml/basic.py
benchml/benchmark.py
benchml/conformal.py
benchml/data.py
benchml/ensemble.py
benchml/hyper.py
benchml/inputs.py
benchml/logger.py
benchml/matrix.py
benchml/pipeline.py
benchml/ptable.py
benchml/readwrite.py
benchml/splits.py
benchml/transforms.py
benchml/utils.py
benchml/descriptors/__init__.py
benchml/descriptors/descr_basic.py
benchml/filters/__init__.py
benchml/filters/random_matrix.py
benchml/kernels/__init__.py
benchml/kernels/kern_basic.py
benchml/models/__init__.py
benchml/models/common.py
benchml/models/mod_basic.py
benchml/models/mod_bench.py
benchml/models/mod_bench_class.py
benchml/models/mod_bench_xtal.py
benchml/models/mod_dscribe.py
benchml/models/mod_logd.py
benchml/models/mod_logd_ai.py
benchml/models/mod_xy.py
benchml/plugins/__init__.py
benchml/plugins/plugin_asap.py
benchml/plugins/plugin_check.py
benchml/plugins/plugin_cx.py
benchml/plugins/plugin_dscribe.py
benchml/plugins/plugin_gylmxx.py
benchml/plugins/plugin_nphil.py
benchml/plugins/plugin_physchem.py
benchml/plugins/plugin_rdkit.py
benchml/plugins/plugin_soap.py
benchml/plugins/plugin_torch.py
benchml/predictors/__init__.py
benchml/predictors/gaussian_process.py
benchml/predictors/pred_sklearn.py
benchml/test/__init__.py
test/__init__.py
test/test_soapgto/__init__.py
BenchML-0.3.4.dist-info/LICENSE.txt
BenchML-0.3.4.dist-info/METADATA
BenchML-0.3.4.dist-info/WHEEL
BenchML-0.3.4.dist-info/top_level.txt
BenchML-0.3.4.dist-info/RECORD
