Metadata-Version: 2.1
Name: BenchML
Version: 0.3.4
Summary: Machine-learning pipelining and benchmarking suite geared towards the physical sciences.
Home-page: https://github.com/capoe/benchml
Author: Carl Poelking
Author-email: cp605@cam.ac.uk
Maintainer: Carl Poelking
Maintainer-email: cp605@cam.ac.uk
License: Apache License 2.0
Keywords: chemical,physicochemical,atomistic,machine learning,pipelining,benchmarking
Classifier: Development Status :: 3 - Alpha
Classifier: Intended Audience :: Science/Research
Classifier: License :: OSI Approved :: Apache Software License
Classifier: Topic :: Scientific/Engineering :: Physics
Classifier: Topic :: Scientific/Engineering :: Chemistry
Classifier: Topic :: Scientific/Engineering :: Artificial Intelligence
Classifier: Programming Language :: Python
Classifier: Programming Language :: Python :: 3
Classifier: Programming Language :: Python :: 3 :: Only
Classifier: Programming Language :: Python :: 3.6
Classifier: Programming Language :: Python :: 3.7
Requires-Python: >=3.6
License-File: LICENSE.txt
Requires-Dist: numpy
Requires-Dist: scipy
Requires-Dist: scikit-learn
